Changelog.md
LICENSE
MANIFEST.in
README.rst
setup.cfg
setup.py
meuhdb/__init__.py
meuhdb/backends.py
meuhdb/core.py
meuhdb/exceptions.py
meuhdb.egg-info/PKG-INFO
meuhdb.egg-info/SOURCES.txt
meuhdb.egg-info/dependency_links.txt
meuhdb.egg-info/not-zip-safe
meuhdb.egg-info/requires.txt
meuhdb.egg-info/top_level.txt