Metadata-Version: 1.0
Name: meuhdb
Version: 0.3.0
Summary: MeuhDB, a database that says "meuh".
Home-page: https://github.com/brunobord/meuhdb/
Author: Bruno Bord
Author-email: bruno@jehaisleprintemps.net
License: MIT License
Platform: UNKNOWN
Classifier: Development Status :: 3 - Alpha
Classifier: Topic :: Database
Classifier: Intended Audience :: Developers
Classifier: License :: OSI Approved
Classifier: License :: OSI Approved :: MIT License
Classifier: Operating System :: OS Independent
Classifier: Programming Language :: Python
Classifier: Programming Language :: Python :: 2
Classifier: Programming Language :: Python :: 2.7
Classifier: Programming Language :: Python :: 3
Classifier: Programming Language :: Python :: 3.3
Classifier: Programming Language :: Python :: 3.4
